robit/__init__.py
robit/config.py
robit/shortcuts.py
robit/core/__init__.py
robit/core/alert.py
robit/core/clock.py
robit/core/counter.py
robit/core/health.py
robit/core/id.py
robit/core/log.py
robit/core/name.py
robit/cron/__init__.py
robit/cron/cron.py
robit/cron/enums.py
robit/cron/fields.py
robit/cron/utils.py
robit/db/__init__.py
robit/db/sqlite.py
robit/db/table.py
robit/db/utils.py
robit/html/__init__.py
robit/html/alpine.js
robit/html/bootstrap.css
robit/html/bootstrap.js
robit/html/core.js
robit/html/icon.png
robit/html/index.css
robit/html/worker.html
robit/html/worker.js
robit/job/__init__.py
robit/job/enums.py
robit/job/group.py
robit/job/job.py
robit/job/tables.py
robit/timer/__init__.py
robit/timer/decorators.py
robit/timer/timer.py
robit/web_server/__init__.py
robit/web_server/request_handler.py
robit/web_server/server.py
robit/web_server/utils.py
robit/worker/__init__.py
robit/worker/worker.py
robit-0.4.9.dist-info/licenses/LICENSE.txt
tests/__init__.py
tests/test_shortcuts.py
tests/core/__init__.py
tests/core/test_alert.py
tests/core/test_clock.py
tests/core/test_counter.py
tests/core/test_health.py
tests/core/test_id.py
tests/core/test_log.py
tests/core/test_name.py
tests/cron/__init__.py
tests/cron/test_cron.py
tests/cron/test_enums.py
tests/cron/test_fields.py
tests/cron/test_utils.py
tests/db/__init__.py
tests/db/test_sqlite.py
tests/db/test_table.py
tests/db/test_utils.py
tests/job/__init__.py
tests/job/test_enums.py
tests/job/test_group.py
tests/job/test_job.py
tests/job/test_tables.py
tests/timer/__init__.py
tests/timer/test_decorators.py
tests/timer/test_timer.py
tests/web_server/__init__.py
tests/web_server/test_request_handler.py
tests/web_server/test_server.py
tests/web_server/test_utils.py
tests/worker/__init__.py
tests/worker/factories.py
tests/worker/test_worker.py
robit-0.4.9.dist-info/METADATA
robit-0.4.9.dist-info/WHEEL
robit-0.4.9.dist-info/top_level.txt
robit-0.4.9.dist-info/RECORD
