Metadata-Version: 2.4
Name: robit
Version: 0.4.9
Summary: Service Worker Framework
Home-page: https://github.com/stratusadv/robit
Author: Nathan Johnson
Author-email: nathanj@stratusadv.com
Keywords: automation,bot,cron,cronjob,chronological,worker,job
Classifier: Programming Language :: Python :: 3
Classifier: License :: OSI Approved :: MIT License
Classifier: Operating System :: OS Independent
Requires-Python: >=3.7
License-File: LICENSE.txt
Requires-Dist: pytz
Dynamic: license-file
